{"project_info":{"project_id":"sharewear-976","project_number":"283481130565","name":"sharewear"},"client":[{"client_info":{"client_id":"android:com.anjoola.sharewear","client_type":1,"android_client_info":{"package_name":"com.anjoola.sharewear"}},"oauth_client":[{"client_id":"283481130565-9orbi5ps2d7hqtu87qpsuagvh05p46kp.apps.googleusercontent.com","client_type":1,"android_info":{"package_name":"com.anjoola.sharewear","certificate_hash":"3a6719721e292e7c425e30a71a7a57ab6989eebf"}}],"services":{"analytics_service":{"status":1},"cloud_messaging_service":{"status":2,"apns_config":[]},"appinvite_service":{"status":1,"other_platform_oauth_client":[]},"google_signin_service":{"status":1},"ads_service":{"status":1}}}],"ARTIFACT_VERSION":"1"}